odoo/addons/pos_analytic_by_config/README.rst
odoo/addons/pos_analytic_by_config/__init__.py
odoo/addons/pos_analytic_by_config/__manifest__.py
odoo/addons/pos_analytic_by_config/i18n/ar.po
odoo/addons/pos_analytic_by_config/i18n/ca.po
odoo/addons/pos_analytic_by_config/i18n/de.po
odoo/addons/pos_analytic_by_config/i18n/el_GR.po
odoo/addons/pos_analytic_by_config/i18n/es.po
odoo/addons/pos_analytic_by_config/i18n/es_MX.po
odoo/addons/pos_analytic_by_config/i18n/fi.po
odoo/addons/pos_analytic_by_config/i18n/fr.po
odoo/addons/pos_analytic_by_config/i18n/it.po
odoo/addons/pos_analytic_by_config/i18n/pos_analytic_by_config.pot
odoo/addons/pos_analytic_by_config/i18n/pt_BR.po
odoo/addons/pos_analytic_by_config/i18n/sk_SK.po
odoo/addons/pos_analytic_by_config/i18n/sl.po
odoo/addons/pos_analytic_by_config/i18n/zh_CN.po
odoo/addons/pos_analytic_by_config/models/__init__.py
odoo/addons/pos_analytic_by_config/models/analytic_distribution_model.py
odoo/addons/pos_analytic_by_config/models/pos_order.py
odoo/addons/pos_analytic_by_config/models/pos_session.py
odoo/addons/pos_analytic_by_config/readme/CONFIGURE.md
odoo/addons/pos_analytic_by_config/readme/CONTRIBUTORS.md
odoo/addons/pos_analytic_by_config/readme/DESCRIPTION.md
odoo/addons/pos_analytic_by_config/readme/ROADMAP.md
odoo/addons/pos_analytic_by_config/readme/USAGE.md
odoo/addons/pos_analytic_by_config/static/description/icon.png
odoo/addons/pos_analytic_by_config/static/description/index.html
odoo/addons/pos_analytic_by_config/tests/__init__.py
odoo/addons/pos_analytic_by_config/tests/test_pos_analytic_by_config.py
odoo/addons/pos_analytic_by_config/views/account_analytic_distribution_model_views.xml
odoo_addon_pos_analytic_by_config-18.0.1.0.1.2.dist-info/METADATA
odoo_addon_pos_analytic_by_config-18.0.1.0.1.2.dist-info/WHEEL
odoo_addon_pos_analytic_by_config-18.0.1.0.1.2.dist-info/top_level.txt
odoo_addon_pos_analytic_by_config-18.0.1.0.1.2.dist-info/RECORD
