Metadata-Version: 2.1
Name: odoo-addon-pos_analytic_by_config
Version: 18.0.1.0.1.2
Requires-Python: >=3.10
Requires-Dist: odoo==18.0.*
Summary: Use analytic account defined on POS configuration for POS orders
Home-page: https://github.com/OCA/account-analytic
License: AGPL-3
Author: ACSONE SA/NV, Tecnativa, Odoo Community Association (OCA)
Author-email: support@odoo-community.org
Classifier: Programming Language :: Python
Classifier: Framework :: Odoo
Classifier: Framework :: Odoo :: 18.0
Classifier: License :: OSI Approved :: GNU Affero General Public License v3
